marrow.mongo-1.1.2-py3.6-nspkg.pth
marrow/mongo/__init__.py
marrow/mongo/geo.py
marrow/mongo/model.py
marrow/mongo/__pycache__/__init__.cpython-36.opt-1.pyc
marrow/mongo/__pycache__/geo.cpython-36.opt-1.pyc
marrow/mongo/__pycache__/model.cpython-36.opt-1.pyc
marrow/mongo/core/__init__.py
marrow/mongo/core/document.py
marrow/mongo/core/index.py
marrow/mongo/core/release.py
marrow/mongo/core/__pycache__/__init__.cpython-36.opt-1.pyc
marrow/mongo/core/__pycache__/document.cpython-36.opt-1.pyc
marrow/mongo/core/__pycache__/index.cpython-36.opt-1.pyc
marrow/mongo/core/__pycache__/release.cpython-36.opt-1.pyc
marrow/mongo/core/field/__init__.py
marrow/mongo/core/field/alias.py
marrow/mongo/core/field/array.py
marrow/mongo/core/field/base.py
marrow/mongo/core/field/binary.py
marrow/mongo/core/field/boolean.py
marrow/mongo/core/field/date.py
marrow/mongo/core/field/decimal_.py
marrow/mongo/core/field/double.py
marrow/mongo/core/field/embed.py
marrow/mongo/core/field/integer.py
marrow/mongo/core/field/link.py
marrow/mongo/core/field/long_.py
marrow/mongo/core/field/mapping.py
marrow/mongo/core/field/md.py
marrow/mongo/core/field/number.py
marrow/mongo/core/field/oid.py
marrow/mongo/core/field/path.py
marrow/mongo/core/field/period.py
marrow/mongo/core/field/plugin.py
marrow/mongo/core/field/reference.py
marrow/mongo/core/field/regex.py
marrow/mongo/core/field/set_.py
marrow/mongo/core/field/string.py
marrow/mongo/core/field/timestamp.py
marrow/mongo/core/field/ttl.py
marrow/mongo/core/field/__pycache__/__init__.cpython-36.opt-1.pyc
marrow/mongo/core/field/__pycache__/alias.cpython-36.opt-1.pyc
marrow/mongo/core/field/__pycache__/array.cpython-36.opt-1.pyc
marrow/mongo/core/field/__pycache__/base.cpython-36.opt-1.pyc
marrow/mongo/core/field/__pycache__/binary.cpython-36.opt-1.pyc
marrow/mongo/core/field/__pycache__/boolean.cpython-36.opt-1.pyc
marrow/mongo/core/field/__pycache__/date.cpython-36.opt-1.pyc
marrow.mongo-1.1.2.dist-info/DESCRIPTION.rst
marrow.mongo-1.1.2.dist-info/METADATA
marrow.mongo-1.1.2.dist-info/RECORD
marrow.mongo-1.1.2.dist-info/WHEEL
marrow.mongo-1.1.2.dist-info/entry_points.txt
marrow.mongo-1.1.2.dist-info/metadata.json
marrow.mongo-1.1.2.dist-info/namespace_packages.txt
marrow.mongo-1.1.2.dist-info/top_level.txt
