Metadata-Version: 2.0
Name: marrow.mongo
Version: 1.1.2
Summary: Light-weight utilities to augment, not replace the Python MongoDB driver.
Home-page: https://github.com/marrow/mongo/
Author: Alice Bevan-McGregor
Author-email: alice@gothcandy.com
License: MIT
Keywords: mongodb,GeoJSON,geospatial,full text,facted,orm,odm,document mapper,declarative,marrow
Platform: UNKNOWN
Classifier: Development Status :: 5 - Production/Stable
Classifier: Intended Audience :: Developers
Classifier: License :: OSI Approved :: MIT License
Classifier: Operating System :: OS Independent
Classifier: Programming Language :: Python
Classifier: Programming Language :: Python :: 2
Classifier: Programming Language :: Python :: 2.7
Classifier: Programming Language :: Python :: 3
Classifier: Programming Language :: Python :: 3.2
Classifier: Programming Language :: Python :: 3.3
Classifier: Programming Language :: Python :: 3.4
Classifier: Programming Language :: Python :: 3.5
Classifier: Programming Language :: Python :: Implementation :: CPython
Classifier: Programming Language :: Python :: Implementation :: PyPy
Classifier: Topic :: Software Development :: Libraries :: Python Modules
Classifier: Topic :: Utilities
Requires-Dist: uri (<3.0.0,>=2.0.0)
Requires-Dist: marrow.schema (<2.0.0,>=1.2.0)
Requires-Dist: marrow.package (<2.0.0,>=1.1.0)
Requires-Dist: pymongo (>=3.2)
Requires-Dist: pathlib2; python_version < "3.4"
Provides-Extra: decimal
Requires-Dist: pymongo (>=3.4); extra == 'decimal'
Provides-Extra: development
Requires-Dist: pytest; extra == 'development'
Requires-Dist: pytest-cov; extra == 'development'
Requires-Dist: pytest-flakes; extra == 'development'
Requires-Dist: pytest-catchlog; extra == 'development'
Requires-Dist: pytest-isort; extra == 'development'
Requires-Dist: misaka; extra == 'development'
Requires-Dist: pygments; extra == 'development'
Requires-Dist: pytz; extra == 'development'
Requires-Dist: tzlocal (>=1.4); extra == 'development'
Requires-Dist: pre-commit; extra == 'development'
Requires-Dist: bandit; extra == 'development'
Provides-Extra: development
Requires-Dist: futures; python_version < "3.4" and extra == 'development'
Provides-Extra: logger
Requires-Dist: tzlocal (>=1.4); extra == 'logger'
Provides-Extra: markdown
Requires-Dist: misaka; extra == 'markdown'
Requires-Dist: pygments; extra == 'markdown'
Provides-Extra: scripting
Requires-Dist: javascripthon (<1.0); extra == 'scripting'
Provides-Extra: timezone
Requires-Dist: pytz; extra == 'timezone'
Requires-Dist: tzlocal (>=1.4); extra == 'timezone'
Provides-Extra: tz
Requires-Dist: pytz; extra == 'tz'
Requires-Dist: tzlocal (>=1.4); extra == 'tz'
